odcp_contracts/__init__.py
odcp_contracts/licensing.py
odcp_contracts/whoami.py
odcp_contracts-0.1.3.dist-info/METADATA
odcp_contracts-0.1.3.dist-info/WHEEL
odcp_contracts-0.1.3.dist-info/top_level.txt
odcp_contracts-0.1.3.dist-info/RECORD
