Metadata-Version: 2.4
Name: odcp-contracts
Version: 0.1.3
Summary: Contracts for Owndivision Control Plane ↔ Data Plane
Requires-Python: >=3.10
Requires-Dist: pydantic[email]<3.0,>=2.7
Requires-Dist: pyjwt<3.0.0,>=2.10.1
